text_token/__init__.py
text_token/text_token.py
text_token-0.9.0b1.dist-info/LICENSE
text_token-0.9.0b1.dist-info/METADATA
text_token-0.9.0b1.dist-info/WHEEL
text_token-0.9.0b1.dist-info/top_level.txt
text_token-0.9.0b1.dist-info/RECORD
