Metadata-Version: 2.1
Name: text-token
Version: 0.9.0b1
Summary: Tokenization of user text.
Author: Shaped Sundew
Project-URL: Homepage, https://github.com/Shapedsundew9/text-token
Project-URL: Bug Tracker, https://github.com/Shapedsundew9/text-token/issues
Classifier: Programming Language :: Python :: 3.11
Classifier: License :: OSI Approved :: MIT License
Classifier: Operating System :: OS Independent
Classifier: Development Status :: 4 - Beta
Requires-Python: >=3.11
License-File: LICENSE
